okmesopy/__init__.py
okmesopy/etcalculator.py
okmesopy/mesonetdownloader.py
okmesopy/mesonettools.py
okmesopy-1.1.5.dist-info/LICENSE
okmesopy-1.1.5.dist-info/METADATA
okmesopy-1.1.5.dist-info/WHEEL
okmesopy-1.1.5.dist-info/top_level.txt
okmesopy-1.1.5.dist-info/RECORD
