Metadata-Version: 2.1
Name: okmesopy
Version: 1.1.5
Summary: Tools to download and manipulate data from OK Mesonet
Home-page: https://github.com/bjrubinstein/okmesopy
Author: Ben Rubinstein
Author-email: brubinst@hawk.iit.edu
License: GNU
Keywords: Mesonet,climatology,meteorology,hydrology
License-File: LICENSE
Requires-Dist: numpy
Requires-Dist: pandas
Requires-Dist: pyshp
Requires-Dist: pyproj
Requires-Dist: geopy
Requires-Dist: missingno
